omniblack/work/__init__.py
omniblack/work/bash_functions/nowrk.bash
omniblack/work/bash_functions/path_funcs.bash
omniblack/work/bash_functions/wrk.bash
omniblack/work/config.py
omniblack/work/default_config.yaml
omniblack/work/env_files/wrk.bash
omniblack/work/env_files/wrk.zsh
omniblack/work/env_reader.py
omniblack/work/functions/nowrk
omniblack/work/functions/wrk
omniblack/work/github_projects.py
omniblack/work/gitlab_projects.py
omniblack/work/mkwrk.py
omniblack/work/projects.py
omniblack/work/rmwrk.py
omniblack/work/wrk_file.py
omniblack.work-0.0.2.dist-info/entry_points.txt
omniblack.work-0.0.2.dist-info/LICENSE.txt
omniblack.work-0.0.2.dist-info/WHEEL
omniblack.work-0.0.2.dist-info/METADATA
omniblack.work-0.0.2.dist-info/RECORD
